.gitignore
LICENSE
README.md
setup.cfg
setup.py
./pharmgkb/__init__.py
./pharmgkb/create_database.py
./pharmgkb/get_clinical_annotation.py
./pharmgkb/get_variant_annotation.py
./pharmgkb/test/__init__.py
./pharmgkb/test/create_database_test.py
./pharmgkb/test/get_clinical_annotation_test.py
./pharmgkb/test/get_variant_annotation_test.py
./utils/__init__.py
./utils/utils.py
iseqpharmgkb.egg-info/PKG-INFO
iseqpharmgkb.egg-info/SOURCES.txt
iseqpharmgkb.egg-info/dependency_links.txt
iseqpharmgkb.egg-info/entry_points.txt
iseqpharmgkb.egg-info/requires.txt
iseqpharmgkb.egg-info/top_level.txt
pharmgkb/__init__.py
pharmgkb/create_database.py
pharmgkb/get_clinical_annotation.py
pharmgkb/get_variant_annotation.py
pharmgkb/test/__init__.py
pharmgkb/test/create_database_test.py
pharmgkb/test/get_clinical_annotation_test.py
pharmgkb/test/get_variant_annotation_test.py
pharmgkb/test/query.json
utils/__init__.py
utils/utils.py