Metadata-Version: 2.1
Name: iseqpharmgkb
Version: 0.0.9
Summary: Package for creating database from PharmGKB and querying for specific variant/allele
Home-page: https://gitlab.com/intelliseq/iseqpharmgkb
Author: Mateusz Marynowski, Olaf Tomaszewski
Author-email: mateusz.marynowski@intelliseq.pl, olaf.tomaszewski@intelliseq.pl
Classifier: Programming Language :: Python :: 3
Classifier: License :: OSI Approved :: MIT License
Classifier: Operating System :: OS Independent
Requires-Python: >=3.6
License-File: LICENSE
